aura_avaw/__init__.py
aura_avaw/main.py
aura_avaw-1.0.0.dist-info/METADATA
aura_avaw-1.0.0.dist-info/WHEEL
aura_avaw-1.0.0.dist-info/top_level.txt
aura_avaw-1.0.0.dist-info/RECORD
