Metadata-Version: 2.4
Name: aura_avaw
Version: 1.0.0
Summary: aura.avaw.ir/document
Home-page: https://github.com/heidarelhaee/aura-py
Author: Heidar Elhaee
Author-email: mr.heidarelhaee@gmail.com
Classifier: Programming Language :: Python :: 3
Classifier: License :: OSI Approved :: MIT License
Classifier: Operating System :: OS Independent
Requires-Python: >=3.7
Requires-Dist: requests
